LICENSE
MANIFEST.in
README.md
setup.py
django_scarface.egg-info/PKG-INFO
django_scarface.egg-info/SOURCES.txt
django_scarface.egg-info/dependency_links.txt
django_scarface.egg-info/requires.txt
django_scarface.egg-info/top_level.txt
scarface/__init__.py
scarface/admin.py
scarface/apps.py
scarface/exceptions.py
scarface/forms.py
scarface/models.py
scarface/platform_strategy.py
scarface/settings.py
scarface/signals.py
scarface/tests.py
scarface/utils.py
scarface/views.py
scarface/management/__init__.py
scarface/management/commands/__init__.py
scarface/management/commands/extract_keys.py
scarface/migrations/0001_initial.py
scarface/migrations/0002_auto_20151217_1017.py
scarface/migrations/0003_auto_20151217_1101.py
scarface/migrations/0004_auto_20151217_1131.py
scarface/migrations/__init__.py